fastapi_filter/__init__.py
fastapi_filter/base/__init__.py
fastapi_filter/base/filter.py
fastapi_filter/contrib/__init__.py
fastapi_filter/contrib/mongoengine/__init__.py
fastapi_filter/contrib/mongoengine/filter.py
fastapi_filter/contrib/sqlalchemy/__init__.py
fastapi_filter/contrib/sqlalchemy/filter.py
fastapi_filter/py.typed
fastapi_filter-0.1.0.dist-info/LICENSE
fastapi_filter-0.1.0.dist-info/WHEEL
fastapi_filter-0.1.0.dist-info/METADATA
fastapi_filter-0.1.0.dist-info/RECORD
