Metadata-Version: 2.1
Name: fastapi-filter
Version: 0.1.0
Summary: FastAPI filter
Home-page: https://github.com/arthurio/fastapi-filter
License: MIT
Author: Arthur Rio
Author-email: arthur.rio44@gmail.com
Requires-Python: >=3.10,<4.0
Classifier: License :: OSI Approved :: MIT License
Classifier: Operating System :: OS Independent
Classifier: Programming Language :: Python
Classifier: Programming Language :: Python :: 3
Classifier: Programming Language :: Python :: 3 :: Only
Classifier: Programming Language :: Python :: 3.10
Provides-Extra: all
Provides-Extra: mongoengine
Provides-Extra: sqlalchemy
Requires-Dist: SQLAlchemy (>=1.4.36,<2.0.0); extra == "sqlalchemy" or extra == "all"
Requires-Dist: fastapi (>=0.78,<0.80)
Requires-Dist: mongoengine (>=0.24.1,<0.25.0); extra == "mongoengine" or extra == "all"
Requires-Dist: pydantic (>=1.9.0,<2.0.0)
Project-URL: Repository, https://github.com/arthurio/fastapi-filter
